dolomite_sfe/__init__.py
dolomite_sfe/read_sfe_images.py
dolomite_sfe/read_spatial_feature_experiment.py
dolomite_sfe/save_spatial_feature_experiment.py
dolomite_sfe-0.0.1.dist-info/licenses/LICENSE.txt
dolomite_sfe-0.0.1.dist-info/METADATA
dolomite_sfe-0.0.1.dist-info/WHEEL
dolomite_sfe-0.0.1.dist-info/top_level.txt
dolomite_sfe-0.0.1.dist-info/RECORD
