Metadata-Version: 2.4
Name: dolomite-sfe
Version: 0.0.1
Summary: ArtifactDB representation for SFE.
Home-page: https://github.com/artifactdb/dolomite-sfe
Author: Jayaram Kancherla
Author-email: jayaram.kancherla@gmail.com
License: MIT
Project-URL: Documentation, https://github.com/artifactdb/dolomite-sfe
Platform: any
Classifier: Development Status :: 4 - Beta
Classifier: Programming Language :: Python
Requires-Python: >=3.9
License-File: LICENSE.txt
Requires-Dist: importlib-metadata; python_version < "3.8"
Requires-Dist: spatialfeatureexperiment>=0.0.3
Requires-Dist: libpysal
Requires-Dist: numpy
Requires-Dist: scipy
Requires-Dist: dolomite_base
Requires-Dist: dolomite_spatial>=0.1.1
Requires-Dist: pyarrow
Requires-Dist: geopandas
Requires-Dist: rasterio
Requires-Dist: aicsimageio
Provides-Extra: testing
Requires-Dist: setuptools; extra == "testing"
Requires-Dist: pytest; extra == "testing"
Requires-Dist: pytest-cov; extra == "testing"
Dynamic: license-file
